jupyter_docker/__init__.py
jupyter_docker/__main__.py
jupyter_docker/__version__.py
jupyter_docker/application.py
jupyter_docker/serverapplication.py
jupyter_docker/handlers/__init__.py
jupyter_docker/handlers/base.py
jupyter_docker/handlers/config/__init__.py
jupyter_docker/handlers/config/handler.py
jupyter_docker/handlers/docker/__init__.py
jupyter_docker/handlers/docker/handler.py
jupyter_docker/handlers/echo/__init__.py
jupyter_docker/handlers/echo/handler.py
jupyter_docker/handlers/index/__init__.py
jupyter_docker/handlers/index/handler.py
jupyter_docker/handlers/ping/__init__.py
jupyter_docker/handlers/ping/handler.py
jupyter_docker/handlers/proxy/__init__.py
jupyter_docker/handlers/proxy/handler.py
jupyter_docker/handlers/relay/__init__.py
jupyter_docker/handlers/relay/handler.py
jupyter_docker/static/README.md
jupyter_docker/templates/index.html
jupyter_docker/tests/__init__.py
jupyter_docker/tests/test_handlers.py
jupyter_docker-0.0.7.data/data/etc/jupyter/jupyter_notebook_config.d/jupyter_docker.json
jupyter_docker-0.0.7.data/data/etc/jupyter/jupyter_server_config.d/jupyter_docker.json
jupyter_docker-0.0.7.dist-info/METADATA
jupyter_docker-0.0.7.dist-info/WHEEL
jupyter_docker-0.0.7.dist-info/entry_points.txt
jupyter_docker-0.0.7.dist-info/licenses/LICENSE
jupyter_docker-0.0.7.dist-info/RECORD
